{"publish_time":"2023-03-04 21:32","forecast":[{"date":"2023-03-03","code1":"0","text1":"\u6674","high":"10","wind1":"5","speed1":"5","code2":"0","text2":"\u6674","low":"-1","wind2":"1","speed2":"5","sun":"06:21|17:46"},{"date":"2023-03-04","code1":"1","text1":"\u591a\u4e91","high":"10","wind1":"2","speed1":"4","code2":"1","text2":"\u591a\u4e91","low":"1","wind2":"3","speed2":"4","sun":"06:24|17:46"},{"date":"2023-03-05","code1":"0","text1":"\u6674","high":"12","wind1":"4","speed1":"6","code2":"0","text2":"\u6674","low":"2","wind2":"4","speed2":"6","sun":"06:22|17:47"},{"date":"2023-03-06","code1":"1","text1":"\u591a\u4e91","high":"15","wind1":"1","speed1":"5","code2":"1","text2":"\u591a\u4e91","low":"2","wind2":"1","speed2":"5","sun":"06:21|17:48"},{"date":"2023-03-07","code1":"1","text1":"\u591a\u4e91","high":"13","wind1":"3","speed1":"5","code2":"0","text2":"\u6674","low":"1","wind2":"3","speed2":"5","sun":"06:19|17:49"},{"date":"2023-03-08","code1":"1","text1":"\u591a\u4e91","high":"14","wind1":"8","speed1":"5","code2":"1","text2":"\u591a\u4e91","low":"0","wind2":"8","speed2":"4","sun":"06:18|17:50"}]}